KarmaDbg-0.1.41.data/scripts/karmadbg_con.py
KarmaDbg-0.1.41.data/scripts/karmadbg_ui.pyw
KarmaDbg-0.1.41.dist-info/DESCRIPTION.rst
KarmaDbg-0.1.41.dist-info/METADATA
KarmaDbg-0.1.41.dist-info/RECORD
KarmaDbg-0.1.41.dist-info/WHEEL
KarmaDbg-0.1.41.dist-info/metadata.json
KarmaDbg-0.1.41.dist-info/top_level.txt
karmadbg/__init__.py
karmadbg/dbgcore/__init__.py
karmadbg/dbgcore/autocomplete.py
karmadbg/dbgcore/dbgdecl.py
karmadbg/dbgcore/dbgengine.py
karmadbg/dbgcore/dbgserver.py
karmadbg/dbgcore/macro.py
karmadbg/dbgcore/nativedbg.py
karmadbg/dbgcore/piperpc.py
karmadbg/dbgcore/pydebug.py
karmadbg/dbgcore/rpcserver.py
karmadbg/dbgcore/settings.py
karmadbg/dbgcore/util.py
karmadbg/dbgcore/varprint.py
karmadbg/macros/__init__.py
karmadbg/macros/config.py
karmadbg/macros/getstarted.py
karmadbg/macros/license.py
karmadbg/macros/stdmacro.py
karmadbg/scripts/__init__.py
karmadbg/scripts/breakpoint.py
karmadbg/scripts/disasm.py
karmadbg/scripts/proclist.py
karmadbg/settings/default.xml
karmadbg/startup/__init__.py
karmadbg/startup/firstrun.py
karmadbg/startup/startup.py
karmadbg/startup/teardown.py
karmadbg/uicore/__init__.py
karmadbg/uicore/async.py
karmadbg/uicore/basewidgets.py
karmadbg/uicore/dbgclient.py
karmadbg/uicore/defaultstyle.py
karmadbg/uicore/stdactions.py
karmadbg/uicore/uicmd.py
karmadbg/uicore/uimanager.py
karmadbg/varprinters/__init__.py
karmadbg/varprinters/basic.py
karmadbg/varprinters/std.py
karmadbg/widgets/__init__.py
karmadbg/widgets/stdwidgetpack/__init__.py
karmadbg/widgets/stdwidgetpack/cmd.py
karmadbg/widgets/stdwidgetpack/cmdext.py
karmadbg/widgets/stdwidgetpack/dbgconsole.py
karmadbg/widgets/stdwidgetpack/dialogs.py
karmadbg/widgets/stdwidgetpack/disasm.py
karmadbg/widgets/stdwidgetpack/dockmgr.py
karmadbg/widgets/stdwidgetpack/localvars.py
karmadbg/widgets/stdwidgetpack/mainmenu.py
karmadbg/widgets/stdwidgetpack/memorydmp.py
karmadbg/widgets/stdwidgetpack/process.py
karmadbg/widgets/stdwidgetpack/pyeval.py
karmadbg/widgets/stdwidgetpack/pylocals.py
karmadbg/widgets/stdwidgetpack/registers.py
karmadbg/widgets/stdwidgetpack/settings.py
karmadbg/widgets/stdwidgetpack/sources.py
