Metadata-Version: 2.0
Name: KarmaDbg
Version: 0.1.41
Summary: Windows native code debugger based on pykd
Home-page: http://karmadbg.codeplex.com
Author: Pykd team
Author-email: pykd.codeplex@hotmail.com
License: UNKNOWN
Platform: UNKNOWN
Requires-Dist: pygments
Requires-Dist: pykd (>=0.3.1.5)
Requires-Dist: pyside (==1.2.2)
